mawaqit/__init__.py
mawaqit/consts.py
mawaqit/mawaqit.py
mawaqit/mawaqit_async.py
mawaqit-1.0.8.dist-info/licenses/LICENSE
mawaqit-1.0.8.dist-info/METADATA
mawaqit-1.0.8.dist-info/WHEEL
mawaqit-1.0.8.dist-info/top_level.txt
mawaqit-1.0.8.dist-info/RECORD
