Metadata-Version: 2.4
Name: mawaqit
Version: 1.0.8
Summary: The official MAWAQIT Python wrapper.
Home-page: https://github.com/mawaqit/mawaqit-py
Author: MAWAQIT
Author-email: support@mawaqit.net
License: MIT
Project-URL: Bug Tracker, https://github.com/mawaqit/mawaqit-py/issues
Classifier: Programming Language :: Python :: 3
Classifier: License :: OSI Approved :: MIT License
Classifier: Operating System :: OS Independent
Requires-Python: >=3.7
License-File: LICENSE
Requires-Dist: aiohttp>=3.8.0
Requires-Dist: backoff>=2.0.0
Dynamic: author
Dynamic: author-email
Dynamic: classifier
Dynamic: description
Dynamic: description-content-type
Dynamic: home-page
Dynamic: license
Dynamic: license-file
Dynamic: project-url
Dynamic: requires-dist
Dynamic: requires-python
Dynamic: summary
